snakemake_storage_plugin_deeporigin/__init__.py
snakemake_storage_plugin_deeporigin-0.0.2.dist-info/LICENSE
snakemake_storage_plugin_deeporigin-0.0.2.dist-info/METADATA
snakemake_storage_plugin_deeporigin-0.0.2.dist-info/WHEEL
snakemake_storage_plugin_deeporigin-0.0.2.dist-info/RECORD
